nupunkt_rs-0.1.1.dist-info/METADATA
nupunkt_rs-0.1.1.dist-info/WHEEL
nupunkt_rs-0.1.1.dist-info/licenses/LICENSE
nupunkt_rs/__init__.py
nupunkt_rs/_nupunkt_rs.abi3.so
nupunkt_rs/debug.py
nupunkt_rs-0.1.1.dist-info/RECORD
