Metadata-Version: 2.4
Name: nupunkt-rs
Version: 0.1.1
Classifier: Development Status :: 4 - Beta
Classifier: Intended Audience :: Developers
Classifier: Intended Audience :: Science/Research
Classifier: Intended Audience :: Legal Industry
Classifier: Intended Audience :: Financial and Insurance Industry
Classifier: License :: OSI Approved :: MIT License
Classifier: Programming Language :: Rust
Classifier: Programming Language :: Python :: Implementation :: CPython
Classifier: Programming Language :: Python :: Implementation :: PyPy
Classifier: Programming Language :: Python :: 3
Classifier: Programming Language :: Python :: 3.11
Classifier: Programming Language :: Python :: 3.12
Classifier: Programming Language :: Python :: 3.13
Classifier: Topic :: Scientific/Engineering :: Artificial Intelligence
Classifier: Topic :: Text Processing :: Linguistic
Classifier: Natural Language :: English
Classifier: Operating System :: OS Independent
Requires-Dist: pytest>=8.3.2 ; extra == 'tests'
Requires-Dist: pytest-benchmark>=5.1.0 ; extra == 'tests'
Requires-Dist: pytest-cov>=6.0.0 ; extra == 'tests'
Requires-Dist: pytest>=8.3.2 ; extra == 'dev'
Requires-Dist: pytest-benchmark>=5.1.0 ; extra == 'dev'
Requires-Dist: pytest-cov>=6.0.0 ; extra == 'dev'
Requires-Dist: maturin>=1.8 ; extra == 'dev'
Requires-Dist: memory-profiler>=0.61.0 ; extra == 'dev'
Requires-Dist: psutil>=7.0.0 ; extra == 'dev'
Provides-Extra: tests
Provides-Extra: dev
License-File: LICENSE
Summary: High-performance Rust implementation of nupunkt sentence/paragraph tokenization
Keywords: nlp,natural language processing,tokenization,sentence boundary detection,paragraph detection,punkt,text processing,linguistics,rust
Home-Page: https://aleainstitute.ai
Author-email: ALEA Institute <hello@aleainstitute.ai>
License: MIT
Requires-Python: >=3.11
Project-URL: Homepage, https://github.com/alea-institute/nupunkt-rs
Project-URL: Source, https://github.com/alea-institute/nupunkt-rs
Project-URL: Bug Tracker, https://github.com/alea-institute/nupunkt-rs/issues
Project-URL: Documentation, https://github.com/alea-institute/nupunkt-rs
